catalystcentersdk/__init__.py
catalystcentersdk/_metadata.py
catalystcentersdk/api/__init__.py
catalystcentersdk/api/authentication.py
catalystcentersdk/api/custom_caller.py
catalystcentersdk/api/v2_3_7_6_1/__init__.py
catalystcentersdk/api/v2_3_7_6_1/ai_endpoint_analytics.py
catalystcentersdk/api/v2_3_7_6_1/application_policy.py
catalystcentersdk/api/v2_3_7_6_1/applications.py
catalystcentersdk/api/v2_3_7_6_1/authentication_management.py
catalystcentersdk/api/v2_3_7_6_1/cisco_trusted_certificates.py
catalystcentersdk/api/v2_3_7_6_1/clients.py
catalystcentersdk/api/v2_3_7_6_1/command_runner.py
catalystcentersdk/api/v2_3_7_6_1/compliance.py
catalystcentersdk/api/v2_3_7_6_1/configuration_archive.py
catalystcentersdk/api/v2_3_7_6_1/configuration_templates.py
catalystcentersdk/api/v2_3_7_6_1/device_onboarding_pnp.py
catalystcentersdk/api/v2_3_7_6_1/device_replacement.py
catalystcentersdk/api/v2_3_7_6_1/devices.py
catalystcentersdk/api/v2_3_7_6_1/disaster_recovery.py
catalystcentersdk/api/v2_3_7_6_1/discovery.py
catalystcentersdk/api/v2_3_7_6_1/eox.py
catalystcentersdk/api/v2_3_7_6_1/event_management.py
catalystcentersdk/api/v2_3_7_6_1/fabric_wireless.py
catalystcentersdk/api/v2_3_7_6_1/file.py
catalystcentersdk/api/v2_3_7_6_1/health_and_performance.py
catalystcentersdk/api/v2_3_7_6_1/issues.py
catalystcentersdk/api/v2_3_7_6_1/itsm.py
catalystcentersdk/api/v2_3_7_6_1/itsm_integration.py
catalystcentersdk/api/v2_3_7_6_1/lan_automation.py
catalystcentersdk/api/v2_3_7_6_1/licenses.py
catalystcentersdk/api/v2_3_7_6_1/network_settings.py
catalystcentersdk/api/v2_3_7_6_1/path_trace.py
catalystcentersdk/api/v2_3_7_6_1/platform.py
catalystcentersdk/api/v2_3_7_6_1/reports.py
catalystcentersdk/api/v2_3_7_6_1/sda.py
catalystcentersdk/api/v2_3_7_6_1/security_advisories.py
catalystcentersdk/api/v2_3_7_6_1/sensors.py
catalystcentersdk/api/v2_3_7_6_1/site_design.py
catalystcentersdk/api/v2_3_7_6_1/sites.py
catalystcentersdk/api/v2_3_7_6_1/software_image_management_swim.py
catalystcentersdk-3.1.3.0.0.dist-info/LICENSE
catalystcentersdk-3.1.3.0.0.dist-info/METADATA
catalystcentersdk-3.1.3.0.0.dist-info/WHEEL
catalystcentersdk-3.1.3.0.0.dist-info/RECORD
