Metadata-Version: 2.3
Name: catalystcentersdk
Version: 3.1.3.0.0
Summary: Cisco CatalystCenter Platform SDK
License: MIT
Keywords: Cisco,CatalystCenter,SDK
Author: Jose Bogarin Solano
Author-email: jbogarin@cloverhound.com
Requires-Python: >=3.8,<4.0
Classifier: License :: OSI Approved :: MIT License
Classifier: Programming Language :: Python :: 3
Classifier: Programming Language :: Python :: 3.8
Classifier: Programming Language :: Python :: 3.9
Classifier: Programming Language :: Python :: 3.10
Classifier: Programming Language :: Python :: 3.11
Classifier: Programming Language :: Python :: 3.12
Classifier: Programming Language :: Python :: 3.13
Requires-Dist: fastjsonschema (>=2.16.2,<3.0.0)
Requires-Dist: requests (>=2.32.0,<3.0.0)
Requires-Dist: requests-toolbelt (>=1.0.0,<2.0.0)
Project-URL: Homepage, https://catalystcentersdk.readthedocs.io/en/latest/
Project-URL: Repository, https://github.com/cisco-en-programmability/catalystcentersdk
